{
    "author": "Author is a reference to the person who created the object. Originals created by Jason didn't have an author specified.",
    "backFootIndex": null,
    "biomes": null,
    "blocksWalking": null,
    "bodyIndex": null,
    "clothing": null,
    "clothingOffsetX": null,
    "clothingOffsetY": null,
    "containSize": null,
    "containable": null,
    "creationSoundForce": null,
    "creationSoundInitialOnly": null,
    "deadlyDistance": null,
    "deathMarker": null,
    "drawBehindPlayer": null,
    "floor": null,
    "floorHugging": null,
    "foodValue": null,
    "frontFootIndex": null,
    "headIndex": null,
    "heatValue": null,
    "heldInHand": null,
    "heldOffsetX": null,
    "heldOffsetY": null,
    "homeMarker": null,
    "id": null,
    "leftBlockingRadius": null,
    "male": null,
    "mapChance": null,
    "minPickupAge": null,
    "name": null,
    "noFlip": null,
    "noSpawn": null,
    "numSlots": null,
    "numSprites": null,
    "numUses": null,
    "numUsesPer": null,
    "permanent": null,
    "person": null,
    "pixHeight": null,
    "rValue": null,
    "rightBlockingRadius": null,
    "sideAccess": null,
    "slotSize": null,
    "slotsLocked": null,
    "sound_creation": null,
    "sound_creation_volume": null,
    "sound_decay": null,
    "sound_decay_volume": null,
    "sound_eating": null,
    "sound_eating_volume": null,
    "sound_using": null,
    "sound_using_volume": null,
    "speedMult": null,
    "sprites": null,
    "tags": null,
    "timeStretch": null,
    "useAppearIndex": null,
    "useDistance": null,
    "useVanishIndex": null,
    "vertSlotRot": null
}